critter/__init__.py
critter/stack.py
critter/version.py
critter-0.1.3.data/scripts/critter
critter-0.1.3.dist-info/LICENSE
critter-0.1.3.dist-info/METADATA
critter-0.1.3.dist-info/NOTICE
critter-0.1.3.dist-info/WHEEL
critter-0.1.3.dist-info/top_level.txt
critter-0.1.3.dist-info/RECORD
