Metadata-Version: 2.1
Name: critter
Version: 0.1.3
Summary: AWS Config Rule Integration TesTER
Home-page: https://github.com/awslabs/critter
Author: Austin Heiman, AWS
Author-email: aheiman@amazon.com
License: Apache License 2.0
Keywords: aws,config,rules,test,testing,integration
Platform: UNKNOWN
Classifier: Development Status :: 4 - Beta
Classifier: Intended Audience :: Developers
Classifier: Topic :: Software Development :: Build Tools
Classifier: License :: OSI Approved :: Apache Software License
Classifier: Programming Language :: Python :: 3
Classifier: Programming Language :: Python :: 3.6
Classifier: Programming Language :: Python :: 3.7
Classifier: Programming Language :: Python :: 3.8
Classifier: Programming Language :: Python :: 3.9
Classifier: Programming Language :: Python :: 3.10
Classifier: Programming Language :: Python :: 3 :: Only
Requires-Python: >= 3.6
License-File: LICENSE
License-File: NOTICE
Requires-Dist: boto3 (>=1.11)
